pycocosn/__init__.py
pycocosn/classes.py
pycocosn/coco.py
pycocosn/colours.py
pycocosn/defaults.py
pycocosn/errors.py
pycocosn/extinction.py
pycocosn/functions.py
pycocosn/kcorr.py
pycocosn/litdata.py
pycocosn/models.py
pycocosn/sims.py
pycocosn/utils.py
pycocosn/version.py
pycocosn/kcorr_data/AB_pseudospectrum.dat
pycocosn/kcorr_data/README
pycocosn/kcorr_data/alpha_lyr_stis_002.dat
pycocosn-0.9.0.dist-info/DESCRIPTION.rst
pycocosn-0.9.0.dist-info/METADATA
pycocosn-0.9.0.dist-info/RECORD
pycocosn-0.9.0.dist-info/WHEEL
pycocosn-0.9.0.dist-info/metadata.json
pycocosn-0.9.0.dist-info/top_level.txt
