Metadata-Version: 2.0
Name: pycocosn
Version: 0.9.0
Summary: Python tools for the CoCo templates
Home-page: https://github.com/RobFirth/pycoco
Author: Rob Firth
Author-email: science@robertfirth.co.uk
License: UNKNOWN
Platform: UNKNOWN
Requires-Dist: numpy
Requires-Dist: matplotlib
Requires-Dist: pandas
Requires-Dist: sqlalchemy
Requires-Dist: astropy
Requires-Dist: sfdmap
Requires-Dist: lmfit
